{"stats":{"minecraft:broken":{"minecraft:shears":11,"minecraft:diamond_shovel":1,"minecraft:diamond_pickaxe":2,"minecraft:iron_hoe":1,"minecraft:iron_pickaxe":3,"minecraft:iron_shovel":2,"minecraft:stone_pickaxe":1,"minecraft:diamond_hoe":1,"minecraft:iron_sword":1,"minecraft:bow":2,"minecraft:stone_sword":1,"minecraft:flint_and_steel":2},"minecraft:mined":{"minecraft:dragon_wall_head":19,"minecraft:cut_sandstone_slab":3,"minecraft:red_shulker_box":205,"minecraft:white_bed":58,"minecraft:granite":7490,"minecraft:acacia_log":352,"minecraft:green_concrete":62,"minecraft:oak_wall_sign":11,"minecraft:nether_wart":28,"minecraft:spawner":1,"minecraft:polished_blackstone_bricks":3,"minecraft:magma_block":919,"minecraft:dark_oak_trapdoor":5,"minecraft:fire":68,"minecraft:barrel":32,"minecraft:nether_brick_stairs":9,"minecraft:white_shulker_box":60,"minecraft:white_banner":6,"minecraft:player_head":2,"minecraft:tripwire":18,"minecraft:sandstone_slab":1,"minecraft:cut_sandstone":607,"minecraft:kelp_plant":97,"minecraft:crimson_nylium":10,"minecraft:torch":2039,"minecraft:note_block":26,"minecraft:melon":314,"minecraft:white_stained_glass_pane":16,"minecraft:dead_bush":3,"minecraft:spruce_wall_sign":3,"minecraft:lime_shulker_box":12,"minecraft:sugar_cane":3901,"minecraft:bricks":347,"minecraft:birch_sapling":7,"minecraft:white_terracotta":2,"minecraft:repeater":56,"minecraft:grass":2967,"minecraft:dark_oak_sapling":1,"minecraft:dark_prismarine":10,"minecraft:mossy_cobblestone":65,"minecraft:dark_oak_log":2456,"minecraft:sea_lantern":36,"minecraft:end_stone":194,"minecraft:spruce_fence":3,"minecraft:redstone_wire":331,"minecraft:red_mushroom":5,"minecraft:redstone_ore":1131,"minecraft:acacia_trapdoor":3,"minecraft:pink_concrete":40,"minecraft:andesite":8832,"minecraft:cobblestone_slab":66,"minecraft:vine":11,"minecraft:rail":52,"minecraft:bone_block":26,"minecraft:ender_chest":226,"minecraft:oak_slab":137,"minecraft:birch_stairs":1,"minecraft:redstone_block":40,"minecraft:glass_pane":7,"minecraft:soul_sand":233,"minecraft:dandelion":57,"minecraft:cornflower":13,"minecraft:campfire":1,"minecraft:purpur_pillar":24,"minecraft:tall_grass":22,"minecraft:diorite":8517,"minecraft:warped_wart_block":70,"minecraft:cobblestone_wall":47,"minecraft:sunflower":3,"minecraft:gravel":4321,"minecraft:cobweb":84,"minecraft:brown_terracotta":2,"minecraft:oak_button":8,"minecraft:birch_sign":7,"minecraft:stone_bricks":704,"minecraft:chipped_anvil":14,"minecraft:gold_ore":177,"minecraft:fern":1,"minecraft:stone_pressure_plate":6,"minecraft:oak_sapling":6,"minecraft:farmland":8,"minecraft:brewing_stand":1,"minecraft:spruce_trapdoor":12,"minecraft:white_concrete":56,"minecraft:polished_diorite":2,"minecraft:composter":61,"minecraft:turtle_egg":2,"minecraft:dragon_head":2,"minecraft:iron_bars":44,"minecraft:spruce_slab":10,"minecraft:brown_shulker_box":88,"minecraft:quartz_block":95,"minecraft:orange_terracotta":3,"minecraft:purpur_stairs":18,"minecraft:light_gray_terracotta":1,"minecraft:end_stone_brick_slab":1,"minecraft:beacon":18,"minecraft:nether_quartz_ore":3257,"minecraft:oak_planks":330,"minecraft:wall_torch":433,"minecraft:cauldron":1,"minecraft:stone_stairs":20,"minecraft:fire_coral_fan":3,"minecraft:blue_terracotta":2,"minecraft:powered_rail":2,"minecraft:dark_oak_slab":2,"minecraft:blue_ice":198,"minecraft:tnt":120,"minecraft:smooth_stone_slab":41,"minecraft:oak_log":3637,"minecraft:beetroots":131,"minecraft:dirt":32871,"minecraft:dispenser":9,"minecraft:ancient_debris":110,"minecraft:quartz_stairs":84,"minecraft:dark_oak_leaves":78,"minecraft:red_stained_glass":2,"minecraft:lever":40,"minecraft:ladder":2,"minecraft:stone_button":8,"minecraft:brown_mushroom_block":178,"minecraft:birch_slab":19,"minecraft:spruce_leaves":113,"minecraft:hay_block":21,"minecraft:light_gray_shulker_box":58,"minecraft:detector_rail":8,"minecraft:gold_block":40,"minecraft:nether_brick_fence":10,"minecraft:bookshelf":44,"minecraft:shroomlight":2,"minecraft:stripped_oak_log":14,"minecraft:wet_sponge":106,"minecraft:acacia_leaves":48,"minecraft:scaffolding":165,"minecraft:magenta_stained_glass":52,"minecraft:snow_block":178,"minecraft:stripped_dark_oak_log":6,"minecraft:basalt":252,"minecraft:polished_granite":4,"minecraft:oak_fence":206,"minecraft:honey_block":34,"minecraft:stone_slab":77,"minecraft:red_concrete":75,"minecraft:prismarine_bricks":21,"minecraft:birch_planks":93,"minecraft:white_wall_banner":1,"minecraft:bee_nest":7,"minecraft:grass_path":333,"minecraft:cocoa":18,"minecraft:yellow_concrete":1148,"minecraft:purple_shulker_box":35,"minecraft:cracked_stone_bricks":44,"minecraft:mossy_stone_bricks":51,"minecraft:jungle_wall_sign":1,"minecraft:dark_oak_planks":332,"minecraft:dark_prismarine_stairs":23,"minecraft:jungle_leaves":47,"minecraft:carved_pumpkin":1,"minecraft:obsidian":924,"minecraft:red_sand":14,"minecraft:stone_brick_wall":1,"minecraft:yellow_carpet":30,"minecraft:jungle_log":392,"minecraft:pink_stained_glass":8,"minecraft:coal_block":128,"minecraft:purpur_slab":21,"minecraft:hopper":93,"minecraft:oxeye_daisy":20,"minecraft:orange_concrete":56,"minecraft:sticky_piston":155,"minecraft:dead_fire_coral_wall_fan":18,"minecraft:pumpkin":651,"minecraft:enchanting_table":3,"minecraft:oak_sign":7,"minecraft:oak_stairs":49,"minecraft:quartz_slab":127,"minecraft:iron_block":2146,"minecraft:piston_head":14,"minecraft:brown_mushroom":6,"minecraft:player_wall_head":1,"minecraft:blast_furnace":4,"minecraft:polished_andesite_stairs":2,"minecraft:glass":66,"minecraft:damaged_anvil":3,"minecraft:spruce_sign":1,"minecraft:polished_diorite_stairs":1,"minecraft:black_concrete_powder":11,"minecraft:wheat":1538,"minecraft:lilac":2,"minecraft:stone_brick_stairs":60,"minecraft:oak_fence_gate":18,"minecraft:blue_shulker_box":7,"minecraft:red_mushroom_block":1,"minecraft:stonecutter":3,"minecraft:piston":68,"minecraft:pink_shulker_box":54,"minecraft:stripped_birch_log":4,"minecraft:shulker_box":657,"minecraft:nether_bricks":1285,"minecraft:jungle_planks":32,"minecraft:yellow_concrete_powder":1,"minecraft:kelp":115,"minecraft:horn_coral_wall_fan":1,"minecraft:snow":759,"minecraft:diamond_block":120,"minecraft:potatoes":617,"minecraft:warped_stem":4,"minecraft:bamboo":130,"minecraft:white_wool":33,"minecraft:smithing_table":6,"minecraft:comparator":13,"minecraft:stone_brick_slab":4,"minecraft:observer":172,"minecraft:spruce_button":2,"minecraft:emerald_ore":24,"minecraft:cyan_concrete_powder":36,"minecraft:sponge":96,"minecraft:dropper":9,"minecraft:white_carpet":111,"minecraft:spruce_log":843,"minecraft:birch_leaves":1638,"minecraft:quartz_pillar":7,"minecraft:dark_oak_sign":1,"minecraft:acacia_planks":64,"minecraft:infested_stone":50,"minecraft:black_shulker_box":86,"minecraft:spruce_planks":36,"minecraft:attached_melon_stem":1,"minecraft:cobblestone_stairs":80,"minecraft:grass_block":27550,"minecraft:soul_soil":441,"minecraft:sandstone_stairs":15,"minecraft:smooth_stone":403,"minecraft:glowstone":191,"minecraft:iron_ore":1413,"minecraft:anvil":53,"minecraft:azure_bluet":12,"minecraft:dark_oak_stairs":12,"minecraft:end_stone_bricks":97,"minecraft:polished_granite_stairs":1,"minecraft:blackstone":1592,"minecraft:melon_stem":3,"minecraft:clay":6,"minecraft:poppy":560,"minecraft:chest":223,"minecraft:mushroom_stem":23,"minecraft:cobblestone":9485,"minecraft:slime_block":240,"minecraft:grindstone":2,"minecraft:prismarine":16,"minecraft:seagrass":30,"minecraft:yellow_wool":1,"minecraft:birch_log":3576,"minecraft:lapis_block":64,"minecraft:birch_trapdoor":14,"minecraft:orange_tulip":7,"minecraft:purpur_block":79,"minecraft:sand":17109,"minecraft:netherrack":30429,"minecraft:oak_leaves":2346,"minecraft:emerald_block":18,"minecraft:nether_gold_ore":79,"minecraft:tube_coral":1,"minecraft:diamond_ore":1186,"minecraft:red_carpet":16,"minecraft:gray_shulker_box":8,"minecraft:brick_stairs":53,"minecraft:white_stained_glass":13,"minecraft:sandstone":6965,"minecraft:oak_trapdoor":69,"minecraft:spruce_sapling":13,"minecraft:furnace":13,"minecraft:carrots":278,"minecraft:dark_oak_fence_gate":15,"minecraft:black_concrete":37,"minecraft:lantern":15,"minecraft:stripped_acacia_log":1,"minecraft:packed_ice":2293,"minecraft:chorus_plant":8,"minecraft:stone":154395,"minecraft:yellow_shulker_box":245,"minecraft:redstone_wall_torch":9,"minecraft:podzol":415,"minecraft:light_blue_shulker_box":39,"minecraft:infested_stone_bricks":9,"minecraft:crafting_table":32,"minecraft:oak_wood":128,"minecraft:rose_bush":212,"minecraft:lectern":286,"minecraft:lapis_ore":296,"minecraft:lily_pad":11,"minecraft:spruce_stairs":18,"minecraft:cactus":28,"minecraft:redstone_torch":12,"minecraft:sweet_berry_bush":108,"minecraft:yellow_bed":14,"minecraft:coal_ore":9363,"minecraft:end_rod":41,"minecraft:terracotta":121,"minecraft:polished_andesite":91,"minecraft:birch_fence":3},"minecraft:crafted":{"minecraft:black_dye":25,"minecraft:yellow_wool":16,"minecraft:oak_sign":30,"minecraft:melon":10800,"minecraft:birch_boat":2,"minecraft:blaze_powder":132,"minecraft:diamond_shovel":13,"minecraft:shulker_box":141,"minecraft:diamond_helmet":18,"minecraft:beacon":1,"minecraft:stone_pressure_plate":55,"minecraft:iron_door":3,"minecraft:name_tag":3,"minecraft:white_shulker_box":5,"minecraft:pink_stained_glass":8,"minecraft:smithing_table":2,"minecraft:sticky_piston":155,"minecraft:painting":1,"minecraft:stone_brick_stairs":56,"minecraft:lectern":14,"minecraft:wooden_hoe":1,"minecraft:stone_slab":294,"minecraft:iron_pickaxe":6,"minecraft:sandstone":49,"minecraft:netherite_ingot":35,"minecraft:composter":7,"minecraft:polished_blackstone_bricks":640,"minecraft:jungle_sign":12,"minecraft:golden_carrot":3816,"minecraft:diamond_hoe":48,"minecraft:blue_shulker_box":1,"minecraft:spruce_fence":18,"minecraft:stone_stairs":16,"minecraft:lantern":84,"minecraft:spruce_stairs":84,"minecraft:light_gray_shulker_box":5,"minecraft:black_concrete_powder":152,"minecraft:red_shulker_box":11,"minecraft:stone_pickaxe":3,"minecraft:quartz_slab":192,"minecraft:spruce_boat":3,"minecraft:enchanting_table":1,"minecraft:acacia_trapdoor":8,"minecraft:red_carpet":60,"minecraft:enchanted_book":107,"minecraft:orange_dye":7,"minecraft:oak_fence_gate":13,"minecraft:chainmail_boots":12,"minecraft:fermented_spider_eye":28,"minecraft:birch_trapdoor":38,"minecraft:writable_book":1,"minecraft:iron_shovel":5,"minecraft:note_block":63,"minecraft:grindstone":1,"minecraft:cobblestone_slab":1306,"minecraft:barrel":26,"minecraft:cooked_chicken":93,"minecraft:stone":46,"minecraft:warped_planks":16,"minecraft:stone_brick_slab":24,"minecraft:bow":16,"minecraft:comparator":104,"minecraft:chest":1627,"minecraft:oak_button":15,"minecraft:bricks":607,"minecraft:ender_eye":126,"minecraft:stone_bricks":3388,"minecraft:oak_fence":180,"minecraft:dropper":10,"minecraft:arrow":120,"minecraft:cauldron":1,"minecraft:brown_dye":6,"minecraft:iron_helmet":3,"minecraft:red_wool":40,"minecraft:white_stained_glass_pane":608,"minecraft:dispenser":9,"minecraft:apple":144,"minecraft:tnt":2969,"minecraft:spruce_trapdoor":26,"minecraft:yellow_dye":160,"minecraft:purple_dye":2,"minecraft:netherite_block":1,"minecraft:stick":4720,"minecraft:iron_ingot":2716,"minecraft:light_blue_shulker_box":3,"minecraft:dark_oak_fence_gate":326,"minecraft:oak_door":12,"minecraft:tripwire_hook":2,"minecraft:fishing_rod":2,"minecraft:spruce_button":4,"minecraft:furnace":29,"minecraft:blast_furnace":1,"minecraft:piston":158,"minecraft:oak_trapdoor":174,"minecraft:flint_and_steel":9,"minecraft:scaffolding":444,"minecraft:cobblestone_wall":54,"minecraft:brown_shulker_box":4,"minecraft:birch_sign":6,"minecraft:purple_shulker_box":2,"minecraft:iron_sword":5,"minecraft:jungle_planks":1088,"minecraft:white_dye":320,"minecraft:stonecutter":2,"minecraft:anvil":12,"minecraft:torch":1284,"minecraft:diamond_chestplate":11,"minecraft:ender_chest":50,"minecraft:smooth_stone":1638,"minecraft:cut_sandstone":6020,"minecraft:cut_sandstone_slab":24,"minecraft:birch_slab":60,"minecraft:slime_block":80,"minecraft:lever":31,"minecraft:bookshelf":100,"minecraft:cooked_mutton":7,"minecraft:iron_bars":688,"minecraft:red_concrete_powder":64,"minecraft:magenta_shulker_box":1,"minecraft:quartz_block":1023,"minecraft:glass":1322,"minecraft:repeater":320,"minecraft:diamond_leggings":16,"minecraft:melon_seeds":38,"minecraft:polished_blackstone":640,"minecraft:birch_door":6,"minecraft:magenta_dye":2,"minecraft:glass_bottle":204,"minecraft:emerald":5767,"minecraft:cooked_porkchop":1,"minecraft:diamond_axe":8,"minecraft:spruce_door":15,"minecraft:hay_block":3,"minecraft:oak_wood":132,"minecraft:lime_shulker_box":2,"minecraft:compass":29,"minecraft:iron_block":470,"minecraft:gold_ingot":558,"minecraft:light_gray_dye":7,"minecraft:birch_stairs":12,"minecraft:yellow_concrete_powder":1168,"minecraft:smooth_stone_slab":30,"minecraft:yellow_bed":2,"minecraft:bone_meal":53874,"minecraft:pink_dye":8,"minecraft:andesite_wall":6,"minecraft:white_carpet":921,"minecraft:diamond":2403,"minecraft:detector_rail":84,"minecraft:ladder":3,"minecraft:spruce_slab":210,"minecraft:diamond_boots":29,"minecraft:redstone_block":210,"minecraft:dark_oak_planks":7355,"minecraft:wheat":163,"minecraft:coal_block":983,"minecraft:daylight_detector":12,"minecraft:white_stained_glass":240,"minecraft:jungle_slab":336,"minecraft:golden_apple":50,"minecraft:gray_shulker_box":4,"minecraft:oak_stairs":192,"minecraft:iron_leggings":3,"minecraft:white_bed":49,"minecraft:brick":2464,"minecraft:oak_planks":11483,"minecraft:dark_oak_boat":1,"minecraft:pink_shulker_box":2,"minecraft:cobblestone_stairs":148,"minecraft:suspicious_stew":2,"minecraft:green_dye":12,"minecraft:hopper":623,"minecraft:iron_boots":3,"minecraft:stone_hoe":3,"minecraft:honeycomb_block":1,"minecraft:item_frame":126,"minecraft:oak_slab":744,"minecraft:map":32,"minecraft:crafting_table":51,"minecraft:spruce_planks":1180,"minecraft:wooden_pickaxe":1,"minecraft:gold_block":48,"minecraft:hopper_minecart":2,"minecraft:birch_planks":5448,"minecraft:brewing_stand":1,"minecraft:pumpkin_seeds":324,"minecraft:black_shulker_box":3,"minecraft:book":310,"minecraft:dark_oak_slab":24,"minecraft:iron_chestplate":13,"minecraft:paper":8074,"minecraft:emerald_block":87,"minecraft:diamond_pickaxe":38,"minecraft:shield":8,"minecraft:birch_fence":114,"minecraft:light_blue_dye":4,"minecraft:stone_sword":2,"minecraft:redstone_torch":1086,"minecraft:sponge":8,"minecraft:shears":34,"minecraft:sandstone_stairs":56,"minecraft:polished_andesite":576,"minecraft:coarse_dirt":128,"minecraft:wooden_sword":1,"minecraft:redstone":2142,"minecraft:coal":153,"minecraft:stone_button":1961,"minecraft:dark_oak_trapdoor":98,"minecraft:gray_dye":4,"minecraft:dark_oak_sign":3,"minecraft:diamond_block":392,"minecraft:glass_pane":128,"minecraft:yellow_shulker_box":5,"minecraft:iron_axe":1,"minecraft:green_concrete_powder":56,"minecraft:iron_hoe":4,"minecraft:slime_ball":150,"minecraft:orange_concrete_powder":56,"minecraft:lime_dye":4,"minecraft:netherite_scrap":107,"minecraft:minecart":33,"minecraft:observer":138,"minecraft:cooked_beef":287,"minecraft:sugar":62,"minecraft:red_dye":131,"minecraft:cooked_cod":25,"minecraft:bone_block":5037,"minecraft:diamond_sword":19,"minecraft:spruce_sign":54,"minecraft:dark_oak_stairs":208,"minecraft:pink_concrete_powder":40,"minecraft:yellow_carpet":9,"minecraft:bell":7,"minecraft:bucket":325,"minecraft:air":0,"minecraft:bread":819,"minecraft:blue_dye":5,"minecraft:oak_boat":14,"minecraft:white_wool":1244,"minecraft:pumpkin_pie":144,"minecraft:acacia_planks":656,"minecraft:lapis_lazuli":531,"minecraft:lapis_block":99,"minecraft:firework_rocket":19223},"minecraft:killed":{"minecraft:tropical_fish":1,"minecraft:salmon":4,"minecraft:ender_dragon":2,"minecraft:pillager":223,"minecraft:donkey":1,"minecraft:zombie":1399,"minecraft:evoker":24,"minecraft:vindicator":103,"minecraft:endermite":14,"minecraft:husk":57,"minecraft:ravager":17,"minecraft:zombified_piglin":76,"minecraft:witch":35,"minecraft:spider":454,"minecraft:wither":1,"minecraft:silverfish":2,"minecraft:piglin":10,"minecraft:zombie_villager":22,"minecraft:sheep":103,"minecraft:trader_llama":8,"minecraft:mooshroom":1,"minecraft:ghast":38,"minecraft:vex":18,"minecraft:slime":766,"minecraft:drowned":36,"minecraft:hoglin":8,"minecraft:squid":24,"minecraft:wither_skeleton":69,"minecraft:villager":2,"minecraft:cave_spider":15,"minecraft:shulker":642,"minecraft:skeleton":1404,"minecraft:chicken":127,"minecraft:cat":1,"minecraft:magma_cube":150,"minecraft:cow":240,"minecraft:horse":9,"minecraft:wandering_trader":5,"minecraft:enderman":43565,"minecraft:wolf":2,"minecraft:pig":9,"minecraft:strider":1,"minecraft:creeper":210,"minecraft:stray":1,"minecraft:blaze":115,"minecraft:phantom":44,"minecraft:llama":1,"minecraft:bat":5},"minecraft:picked_up":{"minecraft:suspicious_stew":6,"minecraft:smithing_table":6,"minecraft:lead":9,"minecraft:stone_slab":290,"minecraft:enchanted_book":20,"minecraft:purple_shulker_box":36,"minecraft:string":1458,"minecraft:pufferfish":8,"minecraft:shroomlight":2,"minecraft:diamond_leggings":84,"minecraft:diamond_ore":598,"minecraft:acacia_log":498,"minecraft:purpur_pillar":27,"minecraft:end_crystal":4,"minecraft:golden_chestplate":16,"minecraft:gray_shulker_box":11,"minecraft:cauldron":1,"minecraft:stone_sword":22,"minecraft:command_block":3,"minecraft:carved_pumpkin":3,"minecraft:red_tulip":2,"minecraft:glowstone":202,"minecraft:end_rod":44,"minecraft:bookshelf":110,"minecraft:blaze_rod":208,"minecraft:iron_bars":71,"minecraft:snowball":109,"minecraft:sponge":149,"minecraft:cooked_beef":661,"minecraft:feather":214,"minecraft:water_bucket":43,"minecraft:dark_oak_boat":30,"minecraft:flint":249,"minecraft:lantern":151,"minecraft:cyan_concrete_powder":19,"minecraft:stonecutter":3,"minecraft:dark_oak_sign":19,"minecraft:diamond_helmet":98,"minecraft:honeycomb":41,"minecraft:dead_fire_coral_fan":15,"minecraft:iron_hoe":2,"minecraft:polished_andesite":72,"minecraft:blue_terracotta":1,"minecraft:lever":66,"minecraft:granite":5778,"minecraft:spruce_button":2,"minecraft:diamond_pickaxe":124,"minecraft:bee_nest":11,"minecraft:clay_ball":12,"minecraft:leather_leggings":22,"minecraft:dragon_head":22,"minecraft:purpur_block":92,"minecraft:cornflower":50,"minecraft:elytra":133,"minecraft:flint_and_steel":20,"minecraft:white_carpet":320,"minecraft:white_stained_glass":10,"minecraft:iron_shovel":13,"minecraft:glass_pane":7,"minecraft:netherite_sword":19,"minecraft:jungle_sapling":9,"minecraft:poppy":489,"minecraft:spruce_slab":12,"minecraft:minecart":31,"minecraft:birch_sapling":249,"minecraft:piston":135,"minecraft:diamond_hoe":33,"minecraft:lime_shulker_box":11,"minecraft:stone":86013,"minecraft:white_dye":1,"minecraft:netherite_pickaxe":28,"minecraft:jungle_sign":1,"minecraft:diamond_chestplate":37,"minecraft:purpur_slab":29,"minecraft:hay_block":22,"minecraft:totem_of_undying":32,"minecraft:mutton":63,"minecraft:rail":135,"minecraft:bone_block":46,"minecraft:emerald_ore":38,"minecraft:oxeye_daisy":41,"minecraft:yellow_shulker_box":253,"minecraft:birch_leaves":1374,"minecraft:yellow_dye":13,"minecraft:purpur_stairs":18,"minecraft:lily_pad":10,"minecraft:paper":413,"minecraft:apple":158,"minecraft:warped_stem":4,"minecraft:oak_fence_gate":15,"minecraft:stone_pickaxe":6,"minecraft:iron_ore":1380,"minecraft:magenta_stained_glass":33,"minecraft:dark_oak_stairs":14,"minecraft:polished_andesite_stairs":2,"minecraft:sweet_berries":209,"minecraft:dragon_egg":1,"minecraft:leather_helmet":12,"minecraft:oak_wood":198,"minecraft:diamond_shovel":81,"minecraft:coal_ore":5508,"minecraft:slime_ball":1670,"minecraft:painting":12,"minecraft:birch_sign":7,"minecraft:baked_potato":127,"minecraft:hopper":51,"minecraft:nether_brick_fence":11,"minecraft:ender_chest":288,"minecraft:yellow_wool":4,"minecraft:stone_brick_stairs":54,"minecraft:lapis_block":28,"minecraft:red_sand":1,"minecraft:smooth_stone":639,"minecraft:comparator":42,"minecraft:bucket":34,"minecraft:red_dye":121,"minecraft:rose_bush":7950,"minecraft:cobblestone_slab":104,"minecraft:wooden_shovel":1,"minecraft:iron_pickaxe":12,"minecraft:tipped_arrow":1,"minecraft:birch_trapdoor":14,"minecraft:spruce_stairs":25,"minecraft:netherite_shovel":21,"minecraft:diorite":6136,"minecraft:rotten_flesh":6382,"minecraft:brown_shulker_box":89,"minecraft:obsidian":1337,"minecraft:blaze_powder":4,"minecraft:cobblestone":12684,"minecraft:enchanting_table":3,"minecraft:leather_chestplate":9,"minecraft:lilac":1,"minecraft:repeater":332,"minecraft:andesite":6596,"minecraft:golden_leggings":7,"minecraft:beacon":19,"minecraft:potato":2199,"minecraft:prismarine_bricks":16,"minecraft:dirt":41092,"minecraft:stripped_birch_log":4,"minecraft:cut_sandstone_slab":5,"minecraft:name_tag":9,"minecraft:glass":769,"minecraft:bone":2874,"minecraft:acacia_planks":133,"minecraft:bow":85,"minecraft:wheat_seeds":5089,"minecraft:orange_tulip":7,"minecraft:grindstone":3,"minecraft:netherite_axe":23,"minecraft:mossy_stone_bricks":59,"minecraft:bamboo":1554,"minecraft:prismarine":13,"minecraft:light_blue_shulker_box":38,"minecraft:melon":3615,"minecraft:nether_brick_stairs":7,"minecraft:grass_block":6350,"minecraft:diamond_block":266,"minecraft:mossy_cobblestone":63,"minecraft:sugar":68,"minecraft:yellow_carpet":42,"minecraft:slime_block":338,"minecraft:netherite_helmet":22,"minecraft:crossbow":16,"minecraft:bone_meal":264,"minecraft:grass":9,"minecraft:golden_apple":31,"minecraft:spruce_sign":4,"minecraft:emerald":1832,"minecraft:netherrack":19620,"minecraft:chorus_fruit":50,"minecraft:oak_leaves":2052,"minecraft:azure_bluet":33,"minecraft:splash_potion":7,"minecraft:ladder":11,"minecraft:brown_mushroom":65,"minecraft:packed_ice":2466,"minecraft:stone_brick_wall":1,"minecraft:shield":14,"minecraft:brick":3,"minecraft:oak_trapdoor":78,"minecraft:birch_fence":38,"minecraft:blackstone":1595,"minecraft:blue_orchid":1,"minecraft:end_stone":293,"minecraft:note_block":26,"minecraft:polished_blackstone_bricks":267,"minecraft:cookie":4,"minecraft:trident":3,"minecraft:brown_dye":2,"minecraft:stone_pressure_plate":6,"minecraft:red_shulker_box":217,"minecraft:pumpkin_pie":2,"minecraft:nether_bricks":1108,"minecraft:brick_stairs":52,"minecraft:netherite_boots":24,"minecraft:basalt":154,"minecraft:golden_carrot":3517,"minecraft:magenta_banner":1,"minecraft:leather":750,"minecraft:yellow_bed":14,"minecraft:cobblestone_wall":132,"minecraft:gunpowder":1818,"minecraft:cooked_mutton":586,"minecraft:red_carpet":26,"minecraft:acacia_trapdoor":2,"minecraft:iron_ingot":1481,"minecraft:cooked_chicken":391,"minecraft:emerald_block":18,"minecraft:nether_quartz_ore":183,"minecraft:stone_brick_slab":2,"minecraft:quartz":6070,"minecraft:dandelion":92,"minecraft:lava_bucket":27,"minecraft:spruce_door":13,"minecraft:polished_diorite_stairs":1,"minecraft:pumpkin_seeds":17,"minecraft:chainmail_leggings":1,"minecraft:terracotta":105,"minecraft:damaged_anvil":7,"minecraft:netherite_hoe":20,"minecraft:end_stone_brick_slab":2,"minecraft:sunflower":270,"minecraft:seagrass":18,"minecraft:birch_door":1,"minecraft:iron_chestplate":27,"minecraft:chainmail_boots":16,"minecraft:flower_pot":4,"minecraft:anvil":153,"minecraft:diamond_sword":108,"minecraft:oak_stairs":40,"minecraft:wither_rose":3,"minecraft:brewing_stand":2,"minecraft:golden_sword":2,"minecraft:dark_oak_trapdoor":5,"minecraft:soul_soil":418,"minecraft:cooked_salmon":17,"minecraft:beetroot":127,"minecraft:gold_nugget":202,"minecraft:spruce_planks":115,"minecraft:coal_block":657,"minecraft:melon_slice":30948,"minecraft:dark_oak_door":6,"minecraft:golden_helmet":12,"minecraft:composter":63,"minecraft:black_dye":32,"minecraft:tropical_fish":6,"minecraft:iron_block":2654,"minecraft:netherite_chestplate":6,"minecraft:birch_log":4071,"minecraft:magma_block":792,"minecraft:iron_door":1,"minecraft:birch_slab":1,"minecraft:jungle_log":483,"minecraft:acacia_leaves":6,"minecraft:netherite_leggings":23,"minecraft:map":2,"minecraft:chipped_anvil":25,"minecraft:glowstone_dust":19,"minecraft:warped_wart_block":48,"minecraft:dropper":19,"minecraft:ink_sac":93,"minecraft:fermented_spider_eye":8,"minecraft:barrel":37,"minecraft:dark_oak_log":2603,"minecraft:stripped_acacia_log":1,"minecraft:dispenser":12,"minecraft:black_concrete_powder":11,"minecraft:green_concrete":62,"minecraft:blue_ice":262,"minecraft:chainmail_helmet":5,"minecraft:bread":661,"minecraft:dark_oak_fence":3,"minecraft:bricks":269,"minecraft:spruce_leaves":1,"minecraft:crafting_table":42,"minecraft:sandstone_slab":1,"minecraft:nether_wart":314,"minecraft:snow":434,"minecraft:compass":28,"minecraft:cracked_stone_bricks":43,"minecraft:beef":383,"minecraft:quartz_stairs":192,"minecraft:chest":261,"minecraft:egg":1186,"minecraft:sandstone":7639,"minecraft:oak_door":11,"minecraft:spruce_fence":5,"minecraft:carrot":1834,"minecraft:redstone":4496,"minecraft:prismarine_crystals":6,"minecraft:tnt":118,"minecraft:polished_granite_stairs":1,"minecraft:cooked_cod":23,"minecraft:beetroot_seeds":350,"minecraft:peony":2,"minecraft:shears":42,"minecraft:diamond_boots":108,"minecraft:sandstone_stairs":23,"minecraft:gold_ingot":35,"minecraft:white_shulker_box":71,"minecraft:white_wool":1197,"minecraft:lapis_ore":205,"minecraft:stripped_oak_log":14,"minecraft:red_mushroom":9,"minecraft:filled_map":176,"minecraft:oak_log":3961,"minecraft:ancient_debris":108,"minecraft:golden_boots":7,"minecraft:white_banner":75,"minecraft:stone_bricks":851,"minecraft:kelp":705,"minecraft:glass_bottle":344,"minecraft:iron_sword":15,"minecraft:dark_oak_slab":10,"minecraft:white_stained_glass_pane":1,"minecraft:yellow_concrete":928,"minecraft:gravel":3370,"minecraft:birch_stairs":1,"minecraft:spruce_sapling":75,"minecraft:spruce_log":828,"minecraft:sea_lantern":36,"minecraft:firework_rocket":8408,"minecraft:red_stained_glass":2,"minecraft:stone_axe":5,"minecraft:redstone_ore":705,"minecraft:diamond_axe":57,"minecraft:oak_button":13,"minecraft:melon_seeds":2,"minecraft:stripped_dark_oak_log":6,"minecraft:ender_pearl":11739,"minecraft:shulker_shell":529,"minecraft:wheat":1697,"minecraft:redstone_block":295,"minecraft:light_gray_shulker_box":60,"minecraft:turtle_egg":2,"minecraft:potion":21,"minecraft:smooth_stone_slab":47,"minecraft:iron_leggings":18,"minecraft:sticky_piston":216,"minecraft:netherite_ingot":1,"minecraft:pink_shulker_box":55,"minecraft:oak_sign":21,"minecraft:black_shulker_box":92,"minecraft:dark_oak_leaves":12,"minecraft:redstone_torch":71,"minecraft:furnace":5,"minecraft:iron_boots":12,"minecraft:stick":684,"minecraft:oak_fence":249,"minecraft:torch":9007,"minecraft:porkchop":9,"minecraft:snow_block":158,"minecraft:yellow_concrete_powder":377,"minecraft:quartz_block":468,"minecraft:nether_gold_ore":59,"minecraft:cactus":98,"minecraft:fire_coral_fan":33,"minecraft:cod":33,"minecraft:nautilus_shell":1,"minecraft:magma_cream":90,"minecraft:wither_skeleton_skull":2,"minecraft:green_shulker_box":1,"minecraft:lapis_lazuli":2437,"minecraft:polished_granite":2,"minecraft:leather_boots":13,"minecraft:bell":2,"minecraft:powered_rail":3,"minecraft:oak_planks":857,"minecraft:stone_hoe":6,"minecraft:ghast_tear":32,"minecraft:pink_stained_glass":8,"minecraft:pink_concrete":40,"minecraft:poisonous_potato":16,"minecraft:jungle_planks":96,"minecraft:sand":18945,"minecraft:dead_bush":3,"minecraft:chiseled_sandstone":1,"minecraft:shulker_box":686,"minecraft:dark_prismarine":10,"minecraft:diamond":1651,"minecraft:spruce_boat":12,"minecraft:black_concrete":37,"minecraft:white_concrete":13,"minecraft:oak_sapling":380,"minecraft:cocoa_beans":100,"minecraft:nether_star":1,"minecraft:end_stone_bricks":93,"minecraft:fishing_rod":3,"minecraft:charcoal":2,"minecraft:chicken":144,"minecraft:wooden_pickaxe":4,"minecraft:gold_block":53,"minecraft:stone_stairs":25,"minecraft:iron_axe":13,"minecraft:orange_concrete":56,"minecraft:wooden_sword":1,"minecraft:item_frame":47,"minecraft:quartz_slab":420,"minecraft:detector_rail":29,"minecraft:dark_prismarine_stairs":24,"minecraft:oak_boat":48,"minecraft:player_head":31,"minecraft:observer":210,"minecraft:lectern":285,"minecraft:blue_shulker_box":6,"minecraft:sugar_cane":8405,"minecraft:spruce_trapdoor":15,"minecraft:phantom_membrane":63,"minecraft:dark_oak_sapling":42,"minecraft:bowl":1,"minecraft:quartz_pillar":7,"minecraft:stone_button":13,"minecraft:magenta_shulker_box":1,"minecraft:dark_oak_planks":961,"minecraft:arrow":2538,"minecraft:saddle":19,"minecraft:wet_sponge":150,"minecraft:salmon":11,"minecraft:cut_sandstone":1452,"minecraft:birch_planks":419,"minecraft:cobblestone_stairs":157,"minecraft:wooden_hoe":1,"minecraft:podzol":324,"minecraft:smooth_sandstone":5,"minecraft:acacia_sapling":17,"minecraft:soul_sand":206,"minecraft:green_dye":2,"minecraft:book":250,"minecraft:oak_slab":211,"minecraft:scaffolding":811,"minecraft:pumpkin":6475,"minecraft:birch_boat":35,"minecraft:blast_furnace":4,"minecraft:white_bed":75,"minecraft:gold_ore":229,"minecraft:dark_oak_fence_gate":15,"minecraft:spider_eye":462,"minecraft:honey_block":19,"minecraft:iron_helmet":24,"minecraft:red_concrete":75,"minecraft:coal":9795},"minecraft:used":{"minecraft:writable_book":5,"minecraft:dispenser":13,"minecraft:poppy":6,"minecraft:stone":21363,"minecraft:quartz_stairs":598,"minecraft:rotten_flesh":17,"minecraft:soul_sand":74,"minecraft:cocoa_beans":34,"minecraft:snowball":48,"minecraft:azure_bluet":3,"minecraft:spruce_boat":14,"minecraft:jungle_sapling":4,"minecraft:packed_ice":1302,"minecraft:lava_bucket":57,"minecraft:quartz_pillar":4,"minecraft:quartz_block":142,"minecraft:netherite_hoe":302,"minecraft:dark_oak_slab":2,"minecraft:bow":2075,"minecraft:oak_sapling":26,"minecraft:cooked_cod":7,"minecraft:dark_prismarine_stairs":9,"minecraft:chorus_fruit":19,"minecraft:lily_pad":10,"minecraft:blackstone":7,"minecraft:cactus":2,"minecraft:wooden_pickaxe":7,"minecraft:composter":67,"minecraft:cut_sandstone_slab":20,"minecraft:blast_furnace":4,"minecraft:acacia_leaves":6,"minecraft:birch_fence":41,"minecraft:birch_slab":40,"minecraft:coal_block":3470,"minecraft:diamond_sword":29174,"minecraft:smithing_table":6,"minecraft:birch_log":788,"minecraft:oak_boat":42,"minecraft:oak_trapdoor":174,"minecraft:enchanting_table":4,"minecraft:orange_concrete":21,"minecraft:carved_pumpkin":1,"minecraft:torch":5394,"minecraft:brewing_stand":2,"minecraft:nether_quartz_ore":98,"minecraft:yellow_carpet":35,"minecraft:oak_fence_gate":23,"minecraft:sea_lantern":25,"minecraft:iron_block":2804,"minecraft:jungle_log":38,"minecraft:barrel":50,"minecraft:basalt":5,"minecraft:wheat_seeds":2165,"minecraft:light_blue_shulker_box":40,"minecraft:birch_planks":260,"minecraft:cauldron":1,"minecraft:diamond_block":147,"minecraft:rail":44,"minecraft:white_bed":94,"minecraft:spruce_log":151,"minecraft:diamond_pickaxe":201239,"minecraft:diamond_shovel":69344,"minecraft:oak_button":18,"minecraft:suspicious_stew":5,"minecraft:spruce_trapdoor":29,"minecraft:spruce_sapling":32,"minecraft:potion":26,"minecraft:cooked_porkchop":2,"minecraft:stripped_oak_log":1,"minecraft:dandelion":15,"minecraft:melon":1842,"minecraft:bone_block":438,"minecraft:nether_wart":65,"minecraft:jungle_planks":45,"minecraft:obsidian":806,"minecraft:bricks":1297,"minecraft:lantern":47,"minecraft:item_frame":166,"minecraft:golden_sword":3,"minecraft:birch_trapdoor":46,"minecraft:blue_shulker_box":7,"minecraft:gold_block":26,"minecraft:pink_concrete_powder":40,"minecraft:dark_oak_sapling":18,"minecraft:end_rod":19,"minecraft:dropper":13,"minecraft:wither_skeleton_skull":3,"minecraft:stone_pickaxe":199,"minecraft:oak_planks":665,"minecraft:sandstone":72,"minecraft:sugar_cane":503,"minecraft:diamond_axe":15680,"minecraft:white_wool":46,"minecraft:yellow_concrete":582,"minecraft:crossbow":20,"minecraft:end_stone":41,"minecraft:sticky_piston":276,"minecraft:dead_fire_coral_fan":12,"minecraft:lever":79,"minecraft:daylight_detector":6,"minecraft:dark_oak_log":356,"minecraft:bread":552,"minecraft:iron_door":1,"minecraft:smooth_stone_slab":74,"minecraft:bone_meal":623,"minecraft:orange_concrete_powder":56,"minecraft:netherite_sword":4943,"minecraft:rose_bush":1339,"minecraft:flint_and_steel":241,"minecraft:redstone":902,"minecraft:ender_chest":233,"minecraft:brown_shulker_box":92,"minecraft:stone_hoe":164,"minecraft:cooked_chicken":234,"minecraft:dirt":17777,"minecraft:bee_nest":5,"minecraft:spruce_fence":17,"minecraft:iron_hoe":522,"minecraft:oak_stairs":174,"minecraft:smooth_sandstone":2,"minecraft:yellow_concrete_powder":785,"minecraft:minecart":44,"minecraft:netherite_pickaxe":60173,"minecraft:cooked_beef":445,"minecraft:turtle_egg":2,"minecraft:pumpkin":11791,"minecraft:cobblestone_stairs":216,"minecraft:snow_block":10,"minecraft:baked_potato":12,"minecraft:birch_boat":35,"minecraft:cut_sandstone":5912,"minecraft:spruce_sign":13,"minecraft:piston":137,"minecraft:wooden_hoe":11,"minecraft:chicken":4,"minecraft:lapis_ore":106,"minecraft:detector_rail":35,"minecraft:stone_slab":252,"minecraft:yellow_wool":1,"minecraft:pink_shulker_box":57,"minecraft:pumpkin_pie":124,"minecraft:birch_stairs":9,"minecraft:spruce_slab":107,"minecraft:ladder":6,"minecraft:chest":1007,"minecraft:white_shulker_box":73,"minecraft:acacia_sapling":3,"minecraft:honey_block":34,"minecraft:netherite_shovel":16687,"minecraft:grass_block":3430,"minecraft:birch_sapling":135,"minecraft:wet_sponge":95,"minecraft:stone_brick_stairs":226,"minecraft:snow":364,"minecraft:dark_oak_boat":31,"minecraft:sweet_berries":12,"minecraft:furnace":28,"minecraft:egg":1255,"minecraft:potato":675,"minecraft:dragon_head":8,"minecraft:magenta_shulker_box":2,"minecraft:diorite":280,"minecraft:end_stone_bricks":32,"minecraft:spruce_door":19,"minecraft:stripped_birch_log":1,"minecraft:acacia_trapdoor":10,"minecraft:powered_rail":3,"minecraft:purpur_pillar":6,"minecraft:oak_leaves":1319,"minecraft:cookie":2,"minecraft:dark_oak_trapdoor":79,"minecraft:purpur_stairs":3,"minecraft:sand":3561,"minecraft:black_concrete_powder":49,"minecraft:pumpkin_seeds":28,"minecraft:stone_button":1960,"minecraft:lectern":293,"minecraft:diamond_ore":576,"minecraft:wooden_sword":219,"minecraft:green_concrete_powder":56,"minecraft:white_stained_glass":19,"minecraft:pink_stained_glass":16,"minecraft:iron_bars":55,"minecraft:stone_sword":220,"minecraft:acacia_log":2,"minecraft:red_concrete":40,"minecraft:netherrack":6517,"minecraft:light_gray_shulker_box":64,"minecraft:dragon_egg":1,"minecraft:anvil":15,"minecraft:stone_stairs":36,"minecraft:red_shulker_box":212,"minecraft:iron_axe":46,"minecraft:brick_stairs":49,"minecraft:spruce_button":5,"minecraft:slime_block":390,"minecraft:totem_of_undying":19,"minecraft:melon_seeds":19,"minecraft:tripwire_hook":2,"minecraft:glowstone":109,"minecraft:beef":1,"minecraft:observer":282,"minecraft:water_bucket":1259,"minecraft:sandstone_stairs":53,"minecraft:yellow_shulker_box":250,"minecraft:polished_blackstone_bricks":644,"minecraft:pink_concrete":21,"minecraft:mossy_cobblestone":2,"minecraft:comparator":108,"minecraft:oak_slab":659,"minecraft:tnt":2816,"minecraft:crafting_table":66,"minecraft:birch_sign":4,"minecraft:dark_oak_fence_gate":327,"minecraft:cod":2,"minecraft:lime_shulker_box":13,"minecraft:oak_log":205,"minecraft:dark_prismarine":10,"minecraft:ender_eye":2,"minecraft:cornflower":5,"minecraft:oxeye_daisy":1,"minecraft:sunflower":8,"minecraft:iron_pickaxe":727,"minecraft:purpur_slab":2,"minecraft:cobblestone":9205,"minecraft:red_concrete_powder":64,"minecraft:glass_pane":50,"minecraft:kelp":304,"minecraft:iron_shovel":885,"minecraft:diamond_hoe":3897,"minecraft:oak_sign":37,"minecraft:iron_sword":512,"minecraft:purple_shulker_box":39,"minecraft:bell":1,"minecraft:player_head":15,"minecraft:nether_bricks":49,"minecraft:carrot":1104,"minecraft:milk_bucket":1,"minecraft:glass":683,"minecraft:coal_ore":3587,"minecraft:quartz_slab":998,"minecraft:hopper_minecart":2,"minecraft:stone_bricks":3400,"minecraft:repeater":318,"minecraft:red_carpet":48,"minecraft:magma_block":682,"minecraft:hay_block":3,"minecraft:scaffolding":912,"minecraft:beetroot_seeds":265,"minecraft:fire_coral_fan":32,"minecraft:dark_oak_stairs":129,"minecraft:birch_leaves":652,"minecraft:dark_oak_sign":3,"minecraft:ender_pearl":1216,"minecraft:redstone_block":71,"minecraft:sponge":106,"minecraft:note_block":76,"minecraft:stone_brick_wall":1,"minecraft:shears":2896,"minecraft:redstone_torch":141,"minecraft:green_concrete":57,"minecraft:black_concrete":37,"minecraft:firework_rocket":264,"minecraft:gray_shulker_box":13,"minecraft:melon_slice":16,"minecraft:string":87,"minecraft:gravel":563,"minecraft:jungle_sign":10,"minecraft:grindstone":3,"minecraft:andesite":471,"minecraft:oak_fence":159,"minecraft:experience_bottle":1,"minecraft:purpur_block":8,"minecraft:trident":288,"minecraft:redstone_ore":389,"minecraft:spruce_planks":143,"minecraft:oak_door":9,"minecraft:white_carpet":798,"minecraft:hopper":700,"minecraft:spruce_stairs":87,"minecraft:cobblestone_wall":44,"minecraft:shulker_box":773,"minecraft:oak_wood":206,"minecraft:granite":193,"minecraft:andesite_wall":4,"minecraft:birch_door":3,"minecraft:stone_brick_slab":21,"minecraft:dark_oak_planks":3679,"minecraft:bookshelf":194,"minecraft:golden_carrot":2959,"minecraft:emerald_block":28,"minecraft:white_stained_glass_pane":509,"minecraft:stone_pressure_plate":34,"minecraft:cooked_mutton":23,"minecraft:iron_ore":28,"minecraft:glass_bottle":66,"minecraft:polished_andesite":617,"minecraft:black_shulker_box":92,"minecraft:magenta_stained_glass":7,"minecraft:beacon":21,"minecraft:stonecutter":5,"minecraft:cobblestone_slab":1052,"minecraft:stripped_dark_oak_log":1,"minecraft:painting":13,"minecraft:apple":7,"minecraft:map":19,"minecraft:netherite_axe":964,"minecraft:fishing_rod":104,"minecraft:white_banner":8,"minecraft:bucket":1563,"minecraft:yellow_bed":15,"minecraft:splash_potion":24,"minecraft:smooth_stone":862},"minecraft:killed_by":{"minecraft:zombie_villager":3,"minecraft:ravager":3,"minecraft:zombie":12,"minecraft:wither":2,"minecraft:skeleton":11,"minecraft:vindicator":1,"minecraft:vex":1,"minecraft:ender_dragon":3,"minecraft:slime":3,"minecraft:wither_skeleton":1,"minecraft:creeper":18,"minecraft:endermite":1,"minecraft:player":11,"minecraft:spider":1,"minecraft:enderman":10},"minecraft:dropped":{"minecraft:iron_sword":6,"minecraft:porkchop":3,"minecraft:lapis_lazuli":93,"minecraft:glass_bottle":51,"minecraft:diamond":163,"minecraft:crafting_table":7,"minecraft:dark_oak_slab":1,"minecraft:cracked_stone_bricks":7,"minecraft:red_mushroom":6,"minecraft:emerald":288,"minecraft:gold_block":29,"minecraft:birch_fence":33,"minecraft:dark_oak_fence":12,"minecraft:dark_oak_trapdoor":1,"minecraft:netherite_boots":3,"minecraft:gold_nugget":14,"minecraft:sand":520,"minecraft:dark_oak_planks":257,"minecraft:fermented_spider_eye":4,"minecraft:fishing_rod":3,"minecraft:white_wool":27,"minecraft:dark_oak_door":3,"minecraft:stone_axe":3,"minecraft:compass":5,"minecraft:diamond_block":68,"minecraft:cooked_chicken":72,"minecraft:netherite_sword":2,"minecraft:wheat":113,"minecraft:obsidian":30,"minecraft:stripped_dark_oak_log":1,"minecraft:rotten_flesh":8144,"minecraft:oak_planks":221,"minecraft:glowstone_dust":24,"minecraft:nether_brick_fence":1,"minecraft:azure_bluet":1,"minecraft:coal_ore":48,"minecraft:quartz_block":1,"minecraft:jungle_log":1,"minecraft:leather_boots":11,"minecraft:acacia_sapling":6,"minecraft:leather_leggings":15,"minecraft:glass":392,"minecraft:beef":27,"minecraft:podzol":4,"minecraft:golden_boots":5,"minecraft:black_dye":3,"minecraft:wheat_seeds":711,"minecraft:netherite_chestplate":1,"minecraft:book":24,"minecraft:prismarine_crystals":6,"minecraft:yellow_carpet":13,"minecraft:golden_apple":3,"minecraft:coal_block":192,"minecraft:lava_bucket":5,"minecraft:dark_oak_leaves":6,"minecraft:ink_sac":9,"minecraft:lapis_ore":1,"minecraft:potion":13,"minecraft:pumpkin":4490,"minecraft:white_banner":16,"minecraft:red_dye":1,"minecraft:smooth_stone":331,"minecraft:chainmail_leggings":1,"minecraft:acacia_planks":76,"minecraft:snow_block":10,"minecraft:yellow_concrete_powder":696,"minecraft:bricks":2,"minecraft:netherite_hoe":1,"minecraft:player_head":6,"minecraft:white_carpet":4,"minecraft:clay_ball":12,"minecraft:iron_boots":8,"minecraft:name_tag":2,"minecraft:oak_sign":1,"minecraft:shears":3,"minecraft:suspicious_stew":4,"minecraft:diamond_sword":28,"minecraft:flower_pot":2,"minecraft:spruce_trapdoor":2,"minecraft:spruce_planks":18,"minecraft:diamond_pickaxe":21,"minecraft:redstone_torch":7,"minecraft:stone_pressure_plate":1,"minecraft:stone_bricks":91,"minecraft:bamboo":177,"minecraft:sandstone":9,"minecraft:bow":31,"minecraft:red_sand":1,"minecraft:terracotta":1,"minecraft:daylight_detector":6,"minecraft:oak_log":268,"minecraft:ender_pearl":4957,"minecraft:dark_oak_sapling":11,"minecraft:green_shulker_box":1,"minecraft:leather":15,"minecraft:jungle_planks":64,"minecraft:cod":16,"minecraft:cobblestone_stairs":9,"minecraft:dark_oak_log":49,"minecraft:packed_ice":1,"minecraft:snowball":1,"minecraft:black_shulker_box":1,"minecraft:wet_sponge":2,"minecraft:black_concrete":1,"minecraft:gold_ingot":4,"minecraft:purpur_block":54,"minecraft:magenta_stained_glass":12,"minecraft:cooked_mutton":30,"minecraft:leather_chestplate":6,"minecraft:beetroot_seeds":81,"minecraft:iron_ore":8,"minecraft:iron_bars":6,"minecraft:scaffolding":2,"minecraft:splash_potion":1,"minecraft:stone_hoe":5,"minecraft:bread":335,"minecraft:golden_helmet":5,"minecraft:yellow_concrete":93,"minecraft:andesite_wall":2,"minecraft:tropical_fish":151,"minecraft:acacia_log":147,"minecraft:iron_block":118,"minecraft:green_dye":5,"minecraft:melon_slice":1712,"minecraft:iron_door":1,"minecraft:cactus":28,"minecraft:chiseled_sandstone":1,"minecraft:kelp":111,"minecraft:sweet_berries":63,"minecraft:oak_trapdoor":1,"minecraft:dark_prismarine_stairs":15,"minecraft:comparator":1,"minecraft:totem_of_undying":9,"minecraft:shulker_box":9,"minecraft:netherite_leggings":1,"minecraft:flint_and_steel":1,"minecraft:andesite":937,"minecraft:golden_leggings":3,"minecraft:oak_sapling":127,"minecraft:birch_sign":7,"minecraft:spruce_log":5,"minecraft:wooden_pickaxe":3,"minecraft:brick":4,"minecraft:cooked_beef":36,"minecraft:emerald_ore":3,"minecraft:sandstone_stairs":9,"minecraft:crossbow":10,"minecraft:saddle":3,"minecraft:purpur_stairs":11,"minecraft:elytra":19,"minecraft:rail":16,"minecraft:cut_sandstone_slab":9,"minecraft:leather_helmet":5,"minecraft:red_carpet":2,"minecraft:item_frame":3,"minecraft:red_shulker_box":3,"minecraft:dirt":2972,"minecraft:melon":534,"minecraft:grass":3,"minecraft:stone_button":2,"minecraft:yellow_dye":2,"minecraft:wooden_sword":1,"minecraft:bone_block":8,"minecraft:bone_meal":84,"minecraft:sunflower":218,"minecraft:phantom_membrane":23,"minecraft:sugar":54,"minecraft:iron_pickaxe":4,"minecraft:dark_oak_boat":2,"minecraft:end_crystal":4,"minecraft:bone":4008,"minecraft:sugar_cane":325,"minecraft:golden_chestplate":6,"minecraft:birch_sapling":23,"minecraft:lime_dye":2,"minecraft:netherite_shovel":2,"minecraft:end_stone":11,"minecraft:blaze_powder":3,"minecraft:white_bed":5,"minecraft:dark_oak_fence_gate":25,"minecraft:salmon":3,"minecraft:charcoal":2,"minecraft:hopper":14,"minecraft:ladder":8,"minecraft:white_dye":51,"minecraft:end_stone_bricks":33,"minecraft:ghast_tear":15,"minecraft:egg":906,"minecraft:enchanted_book":21,"minecraft:iron_ingot":218,"minecraft:netherite_pickaxe":4,"minecraft:netherite_helmet":1,"minecraft:oak_fence":98,"minecraft:purpur_slab":18,"minecraft:feather":100,"minecraft:iron_helmet":16,"minecraft:cobblestone":2001,"minecraft:apple":32,"minecraft:granite":804,"minecraft:command_block":4,"minecraft:spruce_door":4,"minecraft:chainmail_helmet":3,"minecraft:coal":42,"minecraft:pufferfish":8,"minecraft:polished_andesite":1,"minecraft:end_rod":6,"minecraft:oxeye_daisy":1,"minecraft:golden_carrot":300,"minecraft:wooden_hoe":2,"minecraft:rose_bush":3838,"minecraft:diamond_helmet":20,"minecraft:dead_bush":3,"minecraft:iron_shovel":1,"minecraft:paper":121,"minecraft:string":4229,"minecraft:spruce_sapling":10,"minecraft:purpur_pillar":16,"minecraft:furnace":2,"minecraft:redstone_ore":5,"minecraft:netherite_ingot":1,"minecraft:stone_sword":10,"minecraft:cobblestone_wall":14,"minecraft:smooth_stone_slab":7,"minecraft:bowl":5,"minecraft:diamond_hoe":33,"minecraft:chicken":61,"minecraft:slime_block":5,"minecraft:stone_slab":5,"minecraft:diamond_ore":1,"minecraft:nether_bricks":73,"minecraft:pumpkin_seeds":15,"minecraft:potato":4,"minecraft:cobblestone_slab":8,"minecraft:hay_block":2,"minecraft:stone":9344,"minecraft:carved_pumpkin":4,"minecraft:spider_eye":92,"minecraft:birch_boat":1,"minecraft:blue_orchid":1,"minecraft:red_tulip":1,"minecraft:bell":7,"minecraft:quartz_slab":260,"minecraft:gold_ore":1,"minecraft:spruce_sign":1,"minecraft:birch_planks":159,"minecraft:brown_mushroom":16,"minecraft:dark_oak_stairs":4,"minecraft:diamond_axe":9,"minecraft:baked_potato":47,"minecraft:sandstone_slab":1,"minecraft:lantern":41,"minecraft:flint":49,"minecraft:netherite_scrap":2,"minecraft:cornflower":10,"minecraft:cooked_cod":2,"minecraft:cut_sandstone":18,"minecraft:white_stained_glass_pane":1,"minecraft:birch_log":466,"minecraft:gravel":395,"minecraft:blackstone":4,"minecraft:yellow_wool":1,"minecraft:diamond_shovel":12,"minecraft:carrot":275,"minecraft:poppy":3963,"minecraft:shulker_shell":5,"minecraft:oak_fence_gate":2,"minecraft:gunpowder":427,"minecraft:melon_seeds":7,"minecraft:chainmail_boots":24,"minecraft:chest":35,"minecraft:arrow":5288,"minecraft:basalt":128,"minecraft:gray_shulker_box":1,"minecraft:prismarine_bricks":9,"minecraft:quartz":30,"minecraft:oak_leaves":164,"minecraft:netherrack":3397,"minecraft:firework_rocket":1250,"minecraft:water_bucket":7,"minecraft:oak_slab":1,"minecraft:minecart":8,"minecraft:diamond_leggings":13,"minecraft:poisonous_potato":3,"minecraft:lead":3,"minecraft:grass_block":232,"minecraft:stick":267,"minecraft:diorite":1139,"minecraft:torch":144,"minecraft:iron_leggings":11,"minecraft:iron_axe":4,"minecraft:bucket":11,"minecraft:lapis_block":28,"minecraft:dandelion":27,"minecraft:redstone":393,"minecraft:brown_dye":1,"minecraft:ender_chest":3,"minecraft:nether_wart":4,"minecraft:blaze_rod":13,"minecraft:composter":1,"minecraft:iron_hoe":1,"minecraft:ender_eye":6,"minecraft:filled_map":14,"minecraft:snow":7,"minecraft:shield":18,"minecraft:diamond_chestplate":20,"minecraft:iron_chestplate":25,"minecraft:quartz_stairs":10,"minecraft:mossy_stone_bricks":12,"minecraft:oak_boat":13,"minecraft:golden_sword":2,"minecraft:diamond_boots":21,"minecraft:slime_ball":176,"minecraft:stripped_acacia_log":1,"minecraft:beacon":1,"minecraft:stone_pickaxe":3,"minecraft:nether_quartz_ore":2},"minecraft:custom":{"minecraft:interact_with_crafting_table":1899,"minecraft:damage_blocked_by_shield":70,"minecraft:deaths":147,"minecraft:jump":261872,"minecraft:interact_with_cartography_table":2,"minecraft:interact_with_smoker":4,"minecraft:inspect_dispenser":74,"minecraft:horse_one_cm":1285812,"minecraft:inspect_dropper":53,"minecraft:interact_with_anvil":300,"minecraft:inspect_hopper":624,"minecraft:tune_noteblock":435,"minecraft:time_since_rest":11751,"minecraft:swim_one_cm":2591032,"minecraft:open_chest":9461,"minecraft:open_shulker_box":11682,"minecraft:damage_resisted":25455,"minecraft:play_noteblock":70,"minecraft:talked_to_villager":1483,"minecraft:interact_with_brewingstand":60,"minecraft:interact_with_beacon":51,"minecraft:raid_win":10,"minecraft:boat_one_cm":2223876,"minecraft:damage_taken":357129,"minecraft:aviate_one_cm":391294091,"minecraft:open_barrel":917,"minecraft:bell_ring":68,"minecraft:eat_cake_slice":67,"minecraft:leave_game":529,"minecraft:time_since_death":82163,"minecraft:enchant_item":268,"minecraft:interact_with_furnace":509,"minecraft:traded_with_villager":7121,"minecraft:sleep_in_bed":476,"minecraft:damage_dealt":2471025,"minecraft:interact_with_smithing_table":15,"minecraft:target_hit":12,"minecraft:sneak_time":1537019,"minecraft:interact_with_lectern":3,"minecraft:interact_with_blast_furnace":69,"minecraft:interact_with_stonecutter":44,"minecraft:fly_one_cm":85920162,"minecraft:fish_caught":39,"minecraft:fall_one_cm":8921142,"minecraft:animals_bred":221,"minecraft:sprint_one_cm":44389240,"minecraft:drop":4682,"minecraft:walk_on_water_one_cm":1592875,"minecraft:play_one_minute":19374350,"minecraft:open_enderchest":2603,"minecraft:player_kills":20,"minecraft:crouch_one_cm":5546055,"minecraft:mob_kills":53219,"minecraft:climb_one_cm":602427,"minecraft:walk_one_cm":32434771,"minecraft:walk_under_water_one_cm":1839604,"minecraft:raid_trigger":11,"minecraft:interact_with_grindstone":142,"minecraft:damage_absorbed":246,"minecraft:minecart_one_cm":4544}},"DataVersion":2580}